{"id":"de34050f-64cd-48e3-921b-67e8582e8f93","name":"Can-Am Duel 1","status":"closed","condition":"normal","distance":150,"laps":60,"actual_distance":157.5,"purse":0.0,"restrictor_plate":true,"laps_completed":63,"avg_speed":138.124,"victory_margin":"0.207","elapsed_time":"01:08:25","lead_changes":4,"cautions":"4","caution_laps":14,"stage_count":0,"scheduled":"2018-02-16T00:00:00+00:00","start_time":"2018-02-16T00:00:00+00:00","end_time":"2018-02-16T01:30:00+00:00","track":{"name":"Daytona International Speedway","distance":2.5,"shape":"Tri-Oval","banking":"Turns: 31, Tri-Oval: 18, Backstretch: 3","frontstretch":3800,"backstretch":3000,"seating":101000,"id":"6ff97f68-2e9d-4fe6-8cd8-2969e1d3570b"},"comments":"","flags":[{"sequence":1,"lap":-1,"flag_state":"noactiverun"},{"sequence":2,"lap":0,"flag_state":"warmup"},{"sequence":3,"lap":0,"flag_state":"warmup"},{"sequence":4,"lap":0,"flag_state":"green"},{"sequence":5,"lap":8,"flag_state":"yellow","comments":"#10, 19, 48 Incident Frontstretch"},{"sequence":6,"lap":13,"flag_state":"green"},{"sequence":7,"lap":38,"flag_state":"yellow","comments":"#24, 17 Incident Frontstretch"},{"sequence":8,"lap":41,"flag_state":"green"},{"sequence":9,"lap":47,"flag_state":"yellow","comments":"#92 Incident Turn 1"},{"sequence":10,"lap":50,"flag_state":"green"},{"sequence":11,"lap":57,"flag_state":"yellow","comments":"#1, 2 Incident Backstretch"},{"sequence":12,"lap":60,"flag_state":"green"},{"sequence":13,"lap":62,"flag_state":"finish"}],"results":[{"start_position":8,"position":1,"status":"running","driver_rating":119.6,"pit_stops":[{"sequence":1,"lap":0,"leader_lap":0,"positions_gained":0,"in_time":0.0,"out_time":0.0},{"sequence":2,"lap":10,"leader_lap":10,"positions_gained":0,"in_time":698.844,"out_time":724.705}],"best_lap":5,"best_lap_speed":199.996,"best_lap_time":45.001,"elapsed_time":4104.393,"fastest_laps":2,"avg_position":1.937,"avg_speed":138.145,"passes_made":15,"quality_passes":15,"times_passed":9,"passing_differential":6,"last_lap_speed":194.734,"last_lap_time":46.217,"avg_restart_speed":186.303,"points":10,"bonus_points":10,"penalty_points":0,"money":0.0,"laps_led":6,"times_led":1,"laps_completed":63,"car":{"number":"12","sponsors":"Menards/PPG/REV Group/Fitzgerald Gilder Kits","crew_chief":"Jeremy Bullins","id":"874ceeea-76f2-4db9-b647-b10be1082ee4","manufacturer":{"id":"12844047-ab59-43ca-ab6c-c10d54931715","name":"Ford"},"owner":{"id":"3a02ed9a-855e-446a-b71b-876861b84f60","name":"Roger Penske"},"team":{"id":"e337709c-9fb6-4275-ad89-d9c100e71a1d","name":"Team Penske","owner":{"id":"57198af5-d912-4efc-9135-95fc6c0a3fc5","name":"Roger Penske"}}},"driver":{"first_name":"Ryan","last_name":"Blaney","full_name":"Ryan Blaney","points_eligible":true,"id":"67948099-4196-4e1b-ae9e-b437aa99000a"},"leads":[{"sequence":1,"start_lap":58,"end_lap":63}]},{"start_position":6,"position":2,"status":"running","driver_rating":137.3,"pit_stops":[{"sequence":1,"lap":0,"leader_lap":0,"positions_gained":0,"in_time":0.0,"out_time":0.0},{"sequence":2,"lap":10,"leader_lap":10,"positions_gained":0,"in_time":698.598,"out_time":724.703},{"sequence":3,"lap":63,"leader_lap":63,"positions_gained":0,"in_time":4168.388,"out_time":0.0}],"best_lap":5,"best_lap_speed":200.031,"best_lap_time":44.993,"elapsed_time":4104.6,"fastest_laps":3,"avg_position":1.127,"avg_speed":138.138,"passes_made":16,"quality_passes":15,"times_passed":14,"passing_differential":2,"last_lap_speed":194.435,"last_lap_time":46.288,"avg_restart_speed":186.257,"points":9,"bonus_points":9,"penalty_points":0,"money":0.0,"laps_led":56,"times_led":2,"laps_completed":63,"car":{"number":"22","sponsors":"Shell-Pennzoil/AAA/AutoTrader.com","crew_chief":"Todd Gordon","id":"23a4be38-3039-4757-94f5-b4e478e4d7f8","manufacturer":{"id":"12844047-ab59-43ca-ab6c-c10d54931715","name":"Ford"},"owner":{"id":"03246399-5e63-4c21-9c5f-24074e3bf515","name":"Walter Czarnecki"},"team":{"id":"e337709c-9fb6-4275-ad89-d9c100e71a1d","name":"Team Penske","owner":{"id":"57198af5-d912-4efc-9135-95fc6c0a3fc5","name":"Roger Penske"}}},"driver":{"first_name":"Joey","last_name":"Logano","full_name":"Joey Logano","points_eligible":true,"id":"894b273e-ce7d-446c-9ab0-d9a474ce9d7f"},"leads":[{"sequence":1,"start_lap":1,"end_lap":11},{"sequence":2,"start_lap":13,"end_lap":57}]},{"start_position":13,"position":3,"status":"running","driver_rating":96.6,"pit_stops":[{"sequence":1,"lap":0,"leader_lap":0,"positions_gained":0,"in_time":0.0,"out_time":0.0},{"sequence":2,"lap":10,"leader_lap":10,"positions_gained":-4,"in_time":700.138,"out_time":746.998},{"sequence":3,"lap":39,"leader_lap":39,"positions_gained":-1,"in_time":2390.378,"out_time":2423.865},{"sequence":4,"lap":63,"leader_lap":63,"positions_gained":0,"in_time":4173.678,"out_time":0.0}],"best_lap":5,"best_lap_speed":200.089,"best_lap_time":44.98,"elapsed_time":4104.626,"fastest_laps":3,"avg_position":6.429,"avg_speed":138.137,"passes_made":44,"quality_passes":42,"times_passed":35,"passing_differential":9,"last_lap_speed":194.296,"last_lap_time":46.321,"avg_restart_speed":186.306,"points":8,"bonus_points":8,"penalty_points":0,"money":0.0,"laps_led":0,"times_led":0,"laps_completed":63,"car":{"number":"43","sponsors":"Click n' Close/Smithfield/U.S. Air Force/STP","crew_chief":"Drew Blickensderfer","id":"e6fd7d08-83bc-4f2a-8c0b-e5c3cac57ab7","manufacturer":{"id":"dbf04b7a-c4a2-4cff-9dd0-cf1977fc446e","name":"Chevrolet"},"owner":{"id":"1d488f0e-334f-464e-a3db-ae3c8bc028e9","name":"Richard Petty"},"team":{"id":"ee6a924b-58f4-40ea-8514-610936e32e78","name":"Richard Petty Motorsports","owner":{"id":"23972c17-6476-4824-aeb2-43896e2082d9","name":"Richard Petty"}}},"driver":{"first_name":"Darrell","last_name":"Wallace","full_name":"Darrell Wallace Jr","points_eligible":true,"id":"939e647d-756f-41d7-ad65-609344f64bd5"}},{"start_position":5,"position":4,"status":"running","driver_rating":83.8,"pit_stops":[{"sequence":1,"lap":0,"leader_lap":0,"positions_gained":0,"in_time":0.0,"out_time":0.0},{"sequence":2,"lap":10,"leader_lap":10,"positions_gained":1,"in_time":699.505,"out_time":725.411},{"sequence":3,"lap":39,"leader_lap":39,"positions_gained":-7,"in_time":2391.6,"out_time":2488.252},{"sequence":4,"lap":63,"leader_lap":63,"positions_gained":0,"in_time":4171.881,"out_time":0.0}],"best_lap":5,"best_lap_speed":199.769,"best_lap_time":45.052,"elapsed_time":4104.711,"fastest_laps":11,"avg_position":8.937,"avg_speed":138.134,"passes_made":106,"quality_passes":104,"times_passed":105,"passing_differential":1,"last_lap_speed":195.274,"last_lap_time":46.089,"avg_restart_speed":186.174,"points":7,"bonus_points":7,"penalty_points":0,"money":0.0,"laps_led":0,"times_led":0,"laps_completed":63,"car":{"number":"17","sponsors":"Fastenal/Fifth Third Bank/Sunny D","crew_chief":"Brian Pattie","id":"a7fc0b6d-da2f-4cb6-9f7d-154e5351d788","manufacturer":{"id":"12844047-ab59-43ca-ab6c-c10d54931715","name":"Ford"},"owner":{"id":"4788307e-e269-4409-8fae-bbda98214196","name":"Jack Roush"},"team":{"id":"69cd5f7e-cb9d-46c0-a2c3-c1dde01969ee","name":"Roush Fenway Racing"}},"driver":{"first_name":"Ricky","last_name":"Stenhouse","full_name":"Ricky Stenhouse Jr","points_eligible":true,"id":"0cdae85e-0b1d-44d7-9614-a49aff66aeb5"}},{"start_position":9,"position":5,"status":"running","driver_rating":64.3,"pit_stops":[{"sequence":1,"lap":0,"leader_lap":0,"positions_gained":0,"in_time":0.0,"out_time":0.0},{"sequence":2,"lap":10,"leader_lap":10,"positions_gained":-1,"in_time":702.03,"out_time":750.755},{"sequence":3,"lap":12,"leader_lap":13,"positions_gained":0,"in_time":969.398,"out_time":996.005},{"sequence":4,"lap":39,"leader_lap":39,"positions_gained":0,"in_time":2391.916,"out_time":2431.202},{"sequence":5,"lap":63,"leader_lap":63,"positions_gained":0,"in_time":4176.468,"out_time":0.0}],"best_lap":17,"best_lap_speed":199.243,"best_lap_time":45.171,"elapsed_time":4104.725,"fastest_laps":1,"avg_position":9.984,"avg_speed":138.133,"passes_made":68,"quality_passes":67,"times_passed":70,"passing_differential":-2,"last_lap_speed":194.254,"last_lap_time":46.331,"avg_restart_speed":186.193,"points":6,"bonus_points":6,"penalty_points":0,"money":0.0,"laps_led":0,"times_led":0,"laps_completed":63,"car":{"number":"41","sponsors":"Monster Energy/Haas Automation","crew_chief":"Billy Scott","id":"ebb590f6-49ac-4bcd-a06c-9b8f7e38b5a8","manufacturer":{"id":"12844047-ab59-43ca-ab6c-c10d54931715","name":"Ford"},"owner":{"id":"1c6be062-998b-4846-87d0-11eebfe766d8","name":"Gene Haas"},"team":{"id":"876a07ff-ff53-4f23-9528-6d9795270244","name":"Stewart Haas Racing","owner":{"id":"160c7b9e-b198-4b4d-9000-bcdc1a094cee","name":"Tony Stewart"}}},"driver":{"first_name":"Kurt","last_name":"Busch","full_name":"Kurt Busch","points_eligible":true,"id":"8e76a45f-596e-4b56-9eb6-0623e45bf89c"}},{"start_position":11,"position":6,"status":"running","driver_rating":91.0,"pit_stops":[{"sequence":1,"lap":0,"leader_lap":0,"positions_gained":0,"in_time":0.0,"out_time":0.0},{"sequence":2,"lap":10,"leader_lap":10,"positions_gained":0,"in_time":700.885,"out_time":743.891},{"sequence":3,"lap":63,"leader_lap":63,"positions_gained":0,"in_time":4169.295,"out_time":0.0}],"best_lap":5,"best_lap_speed":200.579,"best_lap_time":44.87,"elapsed_time":4104.836,"fastest_laps":1,"avg_position":5.889,"avg_speed":138.13,"passes_made":37,"quality_passes":36,"times_passed":39,"passing_differential":-2,"last_lap_speed":194.003,"last_lap_time":46.391,"avg_restart_speed":186.261,"points":5,"bonus_points":5,"penalty_points":0,"money":0.0,"laps_led":0,"times_led":0,"laps_completed":63,"car":{"number":"31","sponsors":"Caterpillar/Grainger/Liberty National/Bass Pro Shops/Cabela's","crew_chief":"Luke Lambert","id":"c2351769-a323-4eba-8553-ff34d122ffae","manufacturer":{"id":"dbf04b7a-c4a2-4cff-9dd0-cf1977fc446e","name":"Chevrolet"},"owner":{"id":"b28b1f53-bdee-4c44-97fb-bb1fd0ea4a8b","name":"Richard Childress"},"team":{"id":"ffd3ba10-57f2-4bb8-9aaf-7c64b1ba793a","name":"Richard Childress Racing","owner":{"id":"84e3b257-75b1-40ef-8774-cfb53fab90e9","name":"Richard Childress"}}},"driver":{"first_name":"Ryan","last_name":"Newman","full_name":"Ryan Newman","points_eligible":true,"id":"2e6f5ea3-ea6e-48d2-85ec-2e89c2fa02b4"}},{"start_position":20,"position":7,"status":"running","driver_rating":62.8,"pit_stops":[{"sequence":1,"lap":0,"leader_lap":0,"positions_gained":0,"in_time":0.0,"out_time":0.0},{"sequence":2,"lap":10,"leader_lap":10,"positions_gained":2,"in_time":701.216,"out_time":743.449},{"sequence":3,"lap":39,"leader_lap":39,"positions_gained":-1,"in_time":2392.58,"out_time":2439.486},{"sequence":4,"lap":40,"leader_lap":40,"positions_gained":0,"in_time":2440.37,"out_time":0.0},{"sequence":5,"lap":63,"leader_lap":63,"positions_gained":0,"in_time":4176.833,"out_time":0.0}],"best_lap":5,"best_lap_speed":200.758,"best_lap_time":44.83,"elapsed_time":4104.842,"fastest_laps":5,"avg_position":11.175,"avg_speed":138.13,"passes_made":69,"quality_passes":59,"times_passed":70,"passing_differential":-1,"last_lap_speed":194.104,"last_lap_time":46.367,"avg_restart_speed":186.326,"points":4,"bonus_points":4,"penalty_points":0,"money":0.0,"laps_led":0,"times_led":0,"laps_completed":63,"car":{"number":"38","sponsors":"Speedco/1000bulbs.com/Shriners Hospital for Children","crew_chief":"Seth Barbour","id":"122dc137-45ec-41a0-9cf4-c447c34330b4","manufacturer":{"id":"12844047-ab59-43ca-ab6c-c10d54931715","name":"Ford"},"owner":{"id":"69e98f6f-ffa3-4b40-832a-33b262151bba","name":"Brad Jenkins"},"team":{"id":"bd38dfec-bb97-4f29-b032-cc6f0c77dfe6","name":"Front Row Motorsports"}},"driver":{"first_name":"David","last_name":"Ragan","full_name":"David Ragan","points_eligible":true,"id":"25884070-3ded-4fdc-9370-d09428ac95e4"}},{"start_position":4,"position":8,"status":"running","driver_rating":78.4,"pit_stops":[{"sequence":1,"lap":0,"leader_lap":0,"positions_gained":0,"in_time":0.0,"out_time":0.0},{"sequence":2,"lap":8,"leader_lap":9,"positions_gained":0,"in_time":517.237,"out_time":576.809},{"sequence":3,"lap":9,"leader_lap":10,"positions_gained":0,"in_time":647.535,"out_time":710.729},{"sequence":4,"lap":10,"leader_lap":11,"positions_gained":0,"in_time":773.631,"out_time":836.725},{"sequence":5,"lap":39,"leader_lap":39,"positions_gained":-7,"in_time":2391.198,"out_time":2442.788},{"sequence":6,"lap":63,"leader_lap":63,"positions_gained":0,"in_time":4179.982,"out_time":0.0}],"best_lap":5,"best_lap_speed":200.303,"best_lap_time":44.932,"elapsed_time":4104.945,"fastest_laps":3,"avg_position":9.238,"avg_speed":138.126,"passes_made":65,"quality_passes":62,"times_passed":67,"passing_differential":-2,"last_lap_speed":193.986,"last_lap_time":46.395,"avg_restart_speed":186.095,"points":3,"bonus_points":3,"penalty_points":0,"money":0.0,"laps_led":0,"times_led":0,"laps_completed":63,"car":{"number":"19","sponsors":"ARRIS/Ruckus/Stanley/PEAK","crew_chief":"Scott Graves","id":"1e8fcd69-e12e-4fb4-8dff-8b7ec56f3e3f","manufacturer":{"id":"73364deb-a012-4625-b759-db6a236797e3","name":"Toyota"},"owner":{"id":"1ddb24a4-3c7e-4ea5-a5e3-cfb8d405336e","name":"J.D. Gibbs"},"team":{"id":"b30dee06-c437-4e76-8b9c-8b850d52ce21","name":"Joe Gibbs Racing"}},"driver":{"first_name":"Daniel","last_name":"Suarez","full_name":"Daniel Suarez","points_eligible":true,"id":"ebd0a08d-5308-442e-a2ae-2e40aafb3100"}},{"start_position":12,"position":9,"status":"running","driver_rating":82.9,"pit_stops":[{"sequence":1,"lap":0,"leader_lap":0,"positions_gained":0,"in_time":0.0,"out_time":0.0},{"sequence":2,"lap":9,"leader_lap":9,"positions_gained":0,"in_time":570.623,"out_time":659.505},{"sequence":3,"lap":10,"leader_lap":11,"positions_gained":0,"in_time":736.012,"out_time":769.808},{"sequence":4,"lap":12,"leader_lap":13,"positions_gained":0,"in_time":972.355,"out_time":999.06},{"sequence":5,"lap":57,"leader_lap":58,"positions_gained":0,"in_time":3647.482,"out_time":3742.163},{"sequence":6,"lap":59,"leader_lap":59,"positions_gained":0,"in_time":3881.936,"out_time":3920.157},{"sequence":7,"lap":63,"leader_lap":63,"positions_gained":0,"in_time":4178.885,"out_time":0.0}],"best_lap":5,"best_lap_speed":199.871,"best_lap_time":45.029,"elapsed_time":4104.946,"fastest_laps":3,"avg_position":6.905,"avg_speed":138.126,"passes_made":45,"quality_passes":43,"times_passed":32,"passing_differential":13,"last_lap_speed":194.305,"last_lap_time":46.319,"avg_restart_speed":186.539,"points":2,"bonus_points":2,"penalty_points":0,"money":0.0,"laps_led":0,"times_led":0,"laps_completed":63,"car":{"number":"1","sponsors":"McDonald's/Cessna/GearWrench/DC Solar","crew_chief":"Matt McCall","id":"3cc7ae07-4ec7-4d14-8cdf-59557055db30","manufacturer":{"id":"dbf04b7a-c4a2-4cff-9dd0-cf1977fc446e","name":"Chevrolet"},"owner":{"id":"f37e2acb-0f47-498f-8a3c-d2aef410cdc7","name":"Felix Sabates"},"team":{"id":"e9897fd1-8187-4930-814d-5d05cd43d198","name":"Chip Ganassi Racing"}},"driver":{"first_name":"Jamie","last_name":"McMurray","full_name":"Jamie McMurray","points_eligible":true,"id":"f8d8ff36-bfcf-4d98-8eb2-353f1e8d3c34"}},{"start_position":15,"position":10,"status":"running","driver_rating":90.8,"pit_stops":[{"sequence":1,"lap":0,"leader_lap":0,"positions_gained":0,"in_time":0.0,"out_time":0.0},{"sequence":2,"lap":10,"leader_lap":10,"positions_gained":-2,"in_time":700.493,"out_time":746.147},{"sequence":3,"lap":12,"leader_lap":12,"positions_gained":0,"in_time":967.807,"out_time":997.406},{"sequence":4,"lap":48,"leader_lap":48,"positions_gained":-1,"in_time":3063.509,"out_time":3104.966},{"sequence":5,"lap":63,"leader_lap":63,"positions_gained":0,"in_time":4182.329,"out_time":0.0}],"best_lap":5,"best_lap_speed":200.432,"best_lap_time":44.903,"elapsed_time":4105.114,"fastest_laps":0,"avg_position":8.921,"avg_speed":138.12,"passes_made":45,"quality_passes":40,"times_passed":41,"passing_differential":4,"last_lap_speed":194.347,"last_lap_time":46.309,"avg_restart_speed":186.086,"points":1,"bonus_points":1,"penalty_points":0,"money":0.0,"laps_led":0,"times_led":0,"laps_completed":63,"car":{"number":"37","sponsors":"Scott Products/Cottonelle/Kroger/Bush's Beans","crew_chief":"Trent Owens","id":"6a4b77bf-0f1a-45a3-ba5c-2b1e8c51a354","manufacturer":{"id":"dbf04b7a-c4a2-4cff-9dd0-cf1977fc446e","name":"Chevrolet"},"owner":{"id":"db238547-f8d4-4999-9614-0e808d83d766","name":"Tad Geschickter"},"team":{"id":"fb3e4d03-9408-43c6-b65f-61a2399a146d","name":"Team Kroger Clicklist JTG Daugherty Racing","owner":{"id":"30a5532e-cde2-4164-a93d-9b6440fd9725","name":"Tad Geschickter"}}},"driver":{"first_name":"Chris","last_name":"Buescher","full_name":"Chris Buescher","points_eligible":true,"id":"25cfebb6-24e5-429c-a9db-c276bab0e228"}},{"start_position":14,"position":11,"status":"running","driver_rating":62.0,"pit_stops":[{"sequence":1,"lap":0,"leader_lap":0,"positions_gained":0,"in_time":0.0,"out_time":0.0},{"sequence":2,"lap":10,"leader_lap":10,"positions_gained":-1,"in_time":701.583,"out_time":749.189},{"sequence":3,"lap":12,"leader_lap":13,"positions_gained":0,"in_time":969.079,"out_time":1004.3},{"sequence":4,"lap":39,"leader_lap":39,"positions_gained":-1,"in_time":2392.275,"out_time":2436.921},{"sequence":5,"lap":40,"leader_lap":40,"positions_gained":0,"in_time":2523.097,"out_time":2556.464},{"sequence":6,"lap":63,"leader_lap":63,"positions_gained":0,"in_time":4182.486,"out_time":0.0}],"best_lap":55,"best_lap_speed":199.526,"best_lap_time":45.107,"elapsed_time":4105.116,"fastest_laps":4,"avg_position":10.937,"avg_speed":138.12,"passes_made":74,"quality_passes":71,"times_passed":72,"passing_differential":2,"last_lap_speed":194.095,"last_lap_time":46.369,"avg_restart_speed":186.078,"points":0,"bonus_points":0,"penalty_points":0,"money":0.0,"laps_led":0,"times_led":0,"laps_completed":63,"car":{"number":"13","sponsors":"GEICO/Twisted Tea","crew_chief":"Matt Borland","id":"fe0dffc0-6808-4372-8b4c-6c91761a0748","manufacturer":{"id":"dbf04b7a-c4a2-4cff-9dd0-cf1977fc446e","name":"Chevrolet"},"owner":{"id":"55059110-7836-4319-b778-473247e7eb05","name":"Bob Germain Jr."},"team":{"id":"5f6dc3c2-f6a6-44e9-a9a0-90d73570de24","name":"Germain Racing"}},"driver":{"first_name":"Ty","last_name":"Dillon","full_name":"Ty Dillon","id":"bfcb8d32-fab0-4bfa-be14-cf9466e1d886"}},{"start_position":16,"position":12,"status":"running","driver_rating":42.9,"pit_stops":[{"sequence":1,"lap":0,"leader_lap":0,"positions_gained":0,"in_time":0.0,"out_time":0.0},{"sequence":2,"lap":10,"leader_lap":10,"positions_gained":-2,"in_time":702.678,"out_time":761.741},{"sequence":3,"lap":39,"leader_lap":39,"positions_gained":-1,"in_time":2393.48,"out_time":2441.955},{"sequence":4,"lap":44,"leader_lap":45,"positions_gained":0,"in_time":2793.981,"out_time":2826.28},{"sequence":5,"lap":63,"leader_lap":63,"positions_gained":0,"in_time":4186.558,"out_time":0.0}],"best_lap":44,"best_lap_speed":199.159,"best_lap_time":45.19,"elapsed_time":4108.79,"fastest_laps":1,"avg_position":14.619,"avg_speed":137.997,"passes_made":18,"quality_passes":13,"times_passed":20,"passing_differential":-2,"last_lap_speed":188.009,"last_lap_time":47.87,"avg_restart_speed":173.438,"points":0,"bonus_points":0,"penalty_points":0,"money":0.0,"laps_led":0,"times_led":0,"laps_completed":63,"car":{"number":"62","sponsors":"Beard Oil Distributing/TTS Logistics/South Point Hotel & Casino/City Lights Shine ","crew_chief":"Darren Shaw","id":"e220a4c1-eedb-466c-a8d2-850400933538","manufacturer":{"id":"dbf04b7a-c4a2-4cff-9dd0-cf1977fc446e","name":"Chevrolet"},"owner":{"id":"70938928-7a98-42b2-9878-998c78d86767","name":"Mark Beard"},"team":{"id":"0e867fe3-003d-422c-b0ce-04e33bc6a823","name":"Beard Motorsports","owner":{"id":"e0492ba5-c027-40ef-a794-ee139c324fde","name":"Mark Beard"}}},"driver":{"first_name":"Brendan","last_name":"Gaughan","full_name":"Brendan Gaughan","id":"66d6cb11-de3a-4816-9c58-003a76634560"}},{"start_position":18,"position":13,"status":"running","driver_rating":45.7,"pit_stops":[{"sequence":1,"lap":0,"leader_lap":0,"positions_gained":0,"in_time":0.0,"out_time":0.0},{"sequence":2,"lap":10,"leader_lap":10,"positions_gained":8,"in_time":703.872,"out_time":742.753},{"sequence":3,"lap":39,"leader_lap":39,"positions_gained":3,"in_time":2394.176,"out_time":2431.342},{"sequence":4,"lap":48,"leader_lap":48,"positions_gained":1,"in_time":3064.566,"out_time":3098.837},{"sequence":5,"lap":63,"leader_lap":63,"positions_gained":0,"in_time":4189.578,"out_time":0.0}],"best_lap":17,"best_lap_speed":199.623,"best_lap_time":45.085,"elapsed_time":4108.93,"fastest_laps":1,"avg_position":14.444,"avg_speed":137.992,"passes_made":12,"quality_passes":4,"times_passed":19,"passing_differential":-7,"last_lap_speed":188.103,"last_lap_time":47.846,"avg_restart_speed":184.352,"points":0,"bonus_points":0,"penalty_points":0,"money":0.0,"laps_led":0,"times_led":0,"laps_completed":63,"car":{"number":"00","sponsors":"VRX Simulators/StarCom Fiber","crew_chief":"Tony Furr","id":"1325ba3f-a860-4738-8216-43d8a453c906","manufacturer":{"id":"dbf04b7a-c4a2-4cff-9dd0-cf1977fc446e","name":"Chevrolet"},"owner":{"id":"2929145e-242f-4d4f-ae0c-d1a3ed1242ef","name":"Derrike Cope"},"team":{"id":"108ed8c5-066a-47bb-bfbd-651542f7e530","name":"StarCom Racing"}},"driver":{"first_name":"Jeffrey","last_name":"Earnhardt","full_name":"Jeffrey Earnhardt","id":"2e33a0c7-05f0-4887-bcbd-b64606114676"}},{"start_position":1,"position":14,"status":"running","driver_rating":38.8,"pit_stops":[{"sequence":1,"lap":0,"leader_lap":0,"positions_gained":0,"in_time":0.0,"out_time":0.0},{"sequence":2,"lap":11,"leader_lap":11,"positions_gained":0,"in_time":830.469,"out_time":887.826},{"sequence":3,"lap":40,"leader_lap":40,"positions_gained":0,"in_time":2519.737,"out_time":2565.455},{"sequence":4,"lap":48,"leader_lap":48,"positions_gained":0,"in_time":3065.475,"out_time":3105.136},{"sequence":5,"lap":63,"leader_lap":63,"positions_gained":0,"in_time":4197.322,"out_time":0.0}],"best_lap":3,"best_lap_speed":199.605,"best_lap_time":45.089,"elapsed_time":4110.659,"fastest_laps":0,"avg_position":15.746,"avg_speed":137.934,"passes_made":5,"quality_passes":2,"times_passed":19,"passing_differential":-14,"last_lap_speed":192.332,"last_lap_time":46.794,"avg_restart_speed":181.869,"points":0,"bonus_points":0,"penalty_points":0,"money":0.0,"laps_led":0,"times_led":0,"laps_completed":63,"car":{"number":"88","sponsors":"Nationwide Insurance/Axalta/Valvoline","crew_chief":"Greg Ives","id":"04b9f3bc-b614-4102-9ce9-db9fad10020d","manufacturer":{"id":"dbf04b7a-c4a2-4cff-9dd0-cf1977fc446e","name":"Chevrolet"},"owner":{"id":"57fb4b0f-140e-47c6-8710-9e24614b4ff4","name":"Rick Hendrick"},"team":{"id":"8427da4c-9c88-4849-9242-0c184d5ed67c","name":"Hendrick Motorsports","owner":{"id":"df3acab4-1712-44bb-b913-897b4e20fd50","name":"Rick Hendrick"}}},"driver":{"first_name":"Alex","last_name":"Bowman","full_name":"Alex Bowman","id":"3ebef96f-43b4-422a-9d0c-db0127b25384"},"leads":[{"sequence":1,"start_lap":0,"end_lap":0}]},{"start_position":17,"position":15,"status":"running","driver_rating":38.2,"pit_stops":[{"sequence":1,"lap":0,"leader_lap":0,"positions_gained":0,"in_time":0.0,"out_time":0.0},{"sequence":2,"lap":12,"leader_lap":12,"positions_gained":0,"in_time":961.408,"out_time":992.215},{"sequence":3,"lap":39,"leader_lap":39,"positions_gained":8,"in_time":2394.941,"out_time":2423.455},{"sequence":4,"lap":63,"leader_lap":63,"positions_gained":0,"in_time":4197.166,"out_time":0.0}],"best_lap":17,"best_lap_speed":199.632,"best_lap_time":45.083,"elapsed_time":4110.826,"fastest_laps":3,"avg_position":14.619,"avg_speed":137.928,"passes_made":10,"quality_passes":4,"times_passed":13,"passing_differential":-3,"last_lap_speed":184.434,"last_lap_time":48.798,"avg_restart_speed":184.234,"points":0,"bonus_points":0,"penalty_points":0,"money":0.0,"laps_led":1,"times_led":1,"laps_completed":63,"car":{"number":"51","sponsors":"Harry's Shaving Products/Katerra/Keen's Buildings","crew_chief":"Pat Tryson","id":"1e6c455d-a659-4523-8263-66e6544263f9","manufacturer":{"id":"dbf04b7a-c4a2-4cff-9dd0-cf1977fc446e","name":"Chevrolet"},"owner":{"id":"41c22ea5-0caf-459c-9e97-0a13d3e6c086","name":"Rick Ware"},"team":{"id":"115610f5-11b9-43ff-a1b4-ef5cdab18119","name":"Rick Ware Racing"}},"driver":{"first_name":"Justin","last_name":"Marks","full_name":"Justin Marks","id":"8d1f56fe-2dca-42e1-a9ea-e78399ee512e"},"leads":[{"sequence":1,"start_lap":12,"end_lap":12}]},{"start_position":10,"position":16,"status":"accident","driver_rating":90.4,"pit_stops":[{"sequence":1,"lap":0,"leader_lap":0,"positions_gained":0,"in_time":0.0,"out_time":0.0},{"sequence":2,"lap":10,"leader_lap":10,"positions_gained":-1,"in_time":699.141,"out_time":726.559},{"sequence":3,"lap":57,"leader_lap":58,"positions_gained":0,"in_time":3690.902,"out_time":0.0}],"best_lap":5,"best_lap_speed":199.92,"best_lap_time":45.018,"elapsed_time":3597.482,"fastest_laps":1,"avg_position":4.113,"avg_speed":142.6,"passes_made":30,"quality_passes":30,"times_passed":21,"passing_differential":9,"last_lap_speed":194.944,"last_lap_time":46.167,"avg_restart_speed":186.714,"points":0,"bonus_points":0,"penalty_points":0,"money":0.0,"laps_led":0,"times_led":0,"laps_completed":57,"car":{"number":"2","sponsors":"Miller Lite/Discount Tire/Alliance Truck Parts/Wurth/REESE/Draw-Tite","crew_chief":"Paul Wolfe","id":"3d0cf0c8-f933-48ac-a935-71f1d18d4bd5","manufacturer":{"id":"12844047-ab59-43ca-ab6c-c10d54931715","name":"Ford"},"owner":{"id":"3a02ed9a-855e-446a-b71b-876861b84f60","name":"Roger Penske"},"team":{"id":"e337709c-9fb6-4275-ad89-d9c100e71a1d","name":"Team Penske","owner":{"id":"57198af5-d912-4efc-9135-95fc6c0a3fc5","name":"Roger Penske"}}},"driver":{"first_name":"Brad","last_name":"Keselowski","full_name":"Brad Keselowski","id":"0ce4113d-34c8-4272-b658-3b929238dbd3"}},{"start_position":19,"position":17,"status":"accident","driver_rating":28.7,"pit_stops":[{"sequence":1,"lap":0,"leader_lap":0,"positions_gained":0,"in_time":0.0,"out_time":0.0},{"sequence":2,"lap":10,"leader_lap":10,"positions_gained":0,"in_time":703.427,"out_time":760.05},{"sequence":3,"lap":39,"leader_lap":39,"positions_gained":7,"in_time":2395.523,"out_time":2425.376}],"best_lap":3,"best_lap_speed":199.681,"best_lap_time":45.072,"elapsed_time":2884.091,"fastest_laps":1,"avg_position":16.177,"avg_speed":146.667,"passes_made":7,"quality_passes":5,"times_passed":10,"passing_differential":-3,"last_lap_speed":197.036,"last_lap_time":45.677,"avg_restart_speed":184.857,"points":0,"bonus_points":0,"penalty_points":0,"money":0.0,"laps_led":0,"times_led":0,"laps_completed":47,"car":{"number":"92","sponsors":"Black's Tires/CarQuest Auto Parts","crew_chief":"Michael Hester","id":"2757f8ff-b94b-416a-a51d-10286e933534","manufacturer":{"id":"12844047-ab59-43ca-ab6c-c10d54931715","name":"Ford"},"owner":{"id":"2bcff450-f67a-406b-9301-8100d8e6741c","name":"Ricky Benton"},"team":{"id":"d85e8423-08dc-46ab-88f1-ae460fd71a0a","name":"RBR Enterprises"}},"driver":{"first_name":"David","last_name":"Gilliland","full_name":"David Gilliland","id":"81494312-bd6e-40db-a1ad-ae0eda566067"}},{"start_position":3,"position":18,"status":"accident","driver_rating":63.5,"pit_stops":[{"sequence":1,"lap":0,"leader_lap":0,"positions_gained":0,"in_time":0.0,"out_time":0.0},{"sequence":2,"lap":10,"leader_lap":10,"positions_gained":0,"in_time":699.881,"out_time":732.744}],"best_lap":5,"best_lap_speed":199.729,"best_lap_time":45.061,"elapsed_time":2196.846,"fastest_laps":2,"avg_position":11.629,"avg_speed":155.678,"passes_made":47,"quality_passes":46,"times_passed":55,"passing_differential":-8,"last_lap_speed":198.816,"last_lap_time":45.268,"avg_restart_speed":186.02,"points":0,"bonus_points":0,"penalty_points":0,"money":0.0,"laps_led":0,"times_led":0,"laps_completed":38,"car":{"number":"24","sponsors":"Axalta/Liberty University/UniFirst","crew_chief":"Darian Grubb","id":"7cef9b08-2b70-402f-b5b5-c33c623d3126","manufacturer":{"id":"dbf04b7a-c4a2-4cff-9dd0-cf1977fc446e","name":"Chevrolet"},"owner":{"id":"57fb4b0f-140e-47c6-8710-9e24614b4ff4","name":"Rick Hendrick"},"team":{"id":"8427da4c-9c88-4849-9242-0c184d5ed67c","name":"Hendrick Motorsports","owner":{"id":"df3acab4-1712-44bb-b913-897b4e20fd50","name":"Rick Hendrick"}}},"driver":{"first_name":"William","last_name":"Byron","full_name":"William Byron","id":"c9bf58a8-66b6-4d75-a441-c13130ded990"}},{"start_position":2,"position":19,"status":"accident","driver_rating":37.5,"pit_stops":[{"sequence":1,"lap":0,"leader_lap":0,"positions_gained":0,"in_time":0.0,"out_time":0.0}],"best_lap":5,"best_lap_speed":199.703,"best_lap_time":45.067,"elapsed_time":370.239,"fastest_laps":0,"avg_position":15.887,"avg_speed":194.469,"passes_made":11,"quality_passes":10,"times_passed":18,"passing_differential":-7,"last_lap_speed":197.148,"last_lap_time":45.651,"avg_restart_speed":185.058,"points":0,"bonus_points":0,"penalty_points":0,"money":0.0,"laps_led":0,"times_led":0,"laps_completed":8,"car":{"number":"48","sponsors":"Lowe's Home Improvement/Kobalt Tools/Lowe's ProServices/Jimmie Johnson Foundation","crew_chief":"Chad Knaus","id":"733d54fb-e4f5-4829-bc2a-94af6c9c6504","manufacturer":{"id":"dbf04b7a-c4a2-4cff-9dd0-cf1977fc446e","name":"Chevrolet"},"owner":{"id":"492ef62b-a861-4672-9940-0ec3133e04f1","name":"Jeff Gordon"},"team":{"id":"8427da4c-9c88-4849-9242-0c184d5ed67c","name":"Hendrick Motorsports","owner":{"id":"df3acab4-1712-44bb-b913-897b4e20fd50","name":"Rick Hendrick"}}},"driver":{"first_name":"Jimmie","last_name":"Johnson","full_name":"Jimmie Johnson","id":"057da6c6-ad81-4c65-b6b1-64b6da9e2ee7"}},{"start_position":7,"position":20,"status":"accident","driver_rating":34.5,"pit_stops":[{"sequence":1,"lap":0,"leader_lap":0,"positions_gained":0,"in_time":0.0,"out_time":0.0}],"best_lap":5,"best_lap_speed":200.258,"best_lap_time":44.942,"elapsed_time":370.443,"fastest_laps":0,"avg_position":17.194,"avg_speed":194.362,"passes_made":14,"quality_passes":13,"times_passed":13,"passing_differential":1,"last_lap_speed":196.937,"last_lap_time":45.7,"avg_restart_speed":185.562,"points":0,"bonus_points":0,"penalty_points":0,"money":0.0,"laps_led":0,"times_led":0,"laps_completed":8,"car":{"number":"10","sponsors":"Smithfield","crew_chief":"John Klausmeier","id":"2e3b8a4c-5c1c-401d-98b2-7c92bcab23e5","manufacturer":{"id":"12844047-ab59-43ca-ab6c-c10d54931715","name":"Ford"},"owner":{"id":"f605ad11-b0a3-423b-a1f0-220cfa224968","name":"Tony Stewart"},"team":{"id":"876a07ff-ff53-4f23-9528-6d9795270244","name":"Stewart Haas Racing","owner":{"id":"160c7b9e-b198-4b4d-9000-bcdc1a094cee","name":"Tony Stewart"}}},"driver":{"first_name":"Aric","last_name":"Almirola","full_name":"Aric Almirola","id":"e128a081-a2e8-4809-8038-8c936049bf7c"}}]}